stxtools/__init__.py
stxtools/data.py
stxtools/filesystem.py
stx_tools-0.0.5.dist-info/LICENSE.txt
stx_tools-0.0.5.dist-info/METADATA
stx_tools-0.0.5.dist-info/WHEEL
stx_tools-0.0.5.dist-info/top_level.txt
stx_tools-0.0.5.dist-info/RECORD
