Metadata-Version: 2.1
Name: stx-tools
Version: 0.0.5
Summary: Nuestra "Navaja suiza" con clases de python que nos ayudan a crear rápidamente nuestros proyectos.
Home-page: https://github.com/carloxdev/stx-tools
Author: Carlos A. Martínez Jiménez
Author-email: carloxdev@gmail.com
License: UNKNOWN
Download-URL: https://github.com/carloxdev/stx-tools/tarball/0.0.5
Keywords: archivos,python
Platform: UNKNOWN
Classifier: Programming Language :: Python :: 3
Classifier: License :: OSI Approved :: MIT License
Classifier: Operating System :: OS Independent
